lipsync/.gitignore
lipsync/__init__.py
lipsync/audio.py
lipsync/helpers.py
lipsync/hparams.py
lipsync/lipsync.py
lipsync/models/__init__.py
lipsync/models/conv.py
lipsync/models/wav2lip.py
lipsync-0.1.0.dist-info/METADATA
lipsync-0.1.0.dist-info/WHEEL
lipsync-0.1.0.dist-info/RECORD
