Metadata-Version: 2.1
Name: lipsync
Version: 0.1.0
Summary: lipsync is a simple and updated Python library for lip synchronization, based on Wav2Lip. It synchronizes lips in videos and images based on provided audio, supports CPU/CUDA, and uses caching for faster processing.
Home-page: https://github.com/mowshon/lipsync
License: MIT
Keywords: lipsync,lip synchronization,Wav2Lip,audio to video,video processing,speech synchronization
Author: Vasile Buldumac
Author-email: va.buldumac@gmail.com
Requires-Python: >=3.10,<4.0
Classifier: License :: OSI Approved :: MIT License
Classifier: Programming Language :: Python :: 3
Classifier: Programming Language :: Python :: 3.10
Classifier: Programming Language :: Python :: 3.11
Requires-Dist: av (>=14.0.1,<15.0.0)
Requires-Dist: face-alignment (>=1.4.1,<2.0.0)
Requires-Dist: librosa (>=0.10.2.post1,<0.11.0)
Requires-Dist: opencv-python (>=4.10.0.84,<5.0.0.0)
Requires-Dist: torch (>=2.5.1,<3.0.0)
Requires-Dist: tqdm (>=4.67.1,<5.0.0)
Project-URL: Repository, https://github.com/mowshon/lipsync
